seqsee/__init__.py
seqsee/chart_internals.py
seqsee/convert_all.py
seqsee/css.py
seqsee/input_schema.json
seqsee/jsonmaker.py
seqsee/main.py
seqsee/template.html.jinja
seqsee-0.3.1.dist-info/licenses/LICENSE
seqsee-0.3.1.dist-info/METADATA
seqsee-0.3.1.dist-info/WHEEL
seqsee-0.3.1.dist-info/entry_points.txt
seqsee-0.3.1.dist-info/top_level.txt
seqsee-0.3.1.dist-info/RECORD
