Metadata-Version: 2.4
Name: seqsee
Version: 0.3.1
Summary: A generic visualization tool for spectral sequence data
Author-email: Joey Beauvais-Feisthauer <joeybf@wayne.edu>, Dan Isaksen <isaksen@wayne.edu>
License: MIT
Project-URL: Homepage, https://github.com/JoeyBF/SeqSee
Project-URL: Repository, https://github.com/JoeyBF/SeqSee
Project-URL: Documentation, https://github.com/JoeyBF/SeqSee#readme
Project-URL: Issues, https://github.com/JoeyBF/SeqSee/issues
Keywords: spectral-sequence,visualization,mathematics,topology,html
Classifier: Development Status :: 4 - Beta
Classifier: Intended Audience :: Science/Research
Classifier: Topic :: Scientific/Engineering :: Mathematics
Classifier: Topic :: Scientific/Engineering :: Visualization
Classifier: License :: OSI Approved :: MIT License
Requires-Python: >=3.11
License-File: LICENSE
Requires-Dist: compact-json>=1.0.0
Requires-Dist: jinja2>=3.0.0
Requires-Dist: jsonschema>=4.0.0
Requires-Dist: pandas>=2.0.0
Requires-Dist: pydantic>=2.11.4
Dynamic: license-file
